.coveragerc
.dockerignore
.gitignore
.readthedocs.yml
AUTHORS.rst
CHANGELOG.rst
Dockerfile
LICENSE.txt
README.md
config.yml.example
pyproject.toml
setup.cfg
setup.py
tox.ini
docs/Makefile
docs/authors.rst
docs/changelog.rst
docs/conf.py
docs/index.rst
docs/license.rst
docs/readme.rst
docs/requirements.txt
docs/_static/.gitignore
resources/chromedriver.exe
src/homescraper/__init__.py
src/homescraper/config.py
src/homescraper/datatypes.py
src/homescraper/db.py
src/homescraper/exceptions.py
src/homescraper/http.py
src/homescraper/main.py
src/homescraper/notification.py
src/homescraper/providers.py
src/homescraper/scraper.py
src/homescraper.egg-info/PKG-INFO
src/homescraper.egg-info/SOURCES.txt
src/homescraper.egg-info/dependency_links.txt
src/homescraper.egg-info/entry_points.txt
src/homescraper.egg-info/not-zip-safe
src/homescraper.egg-info/requires.txt
src/homescraper.egg-info/top_level.txt
tests/conftest.py
tests/test_db.py
tests/test_providers.py